d42/__init__.py
d42/__main__.py
d42/_main.py
d42/py.typed
d42/custom_type/__init__.py
d42/custom_type/_custom_type.py
d42/custom_type/errors.py
d42/custom_type/utils.py
d42/custom_type/visitors.py
d42/declaration/__init__.py
d42/declaration/_is_ellipsis.py
d42/declaration/_props.py
d42/declaration/_schema_facade.py
d42/declaration/_schema_visitor.py
d42/declaration/errors/__init__.py
d42/declaration/types/__init__.py
d42/declaration/types/_any_schema.py
d42/declaration/types/_bool_schema.py
d42/declaration/types/_bytes_schema.py
d42/declaration/types/_date_schema.py
d42/declaration/types/_datetime_schema.py
d42/declaration/types/_dict_schema.py
d42/declaration/types/_float_schema.py
d42/declaration/types/_int_schema.py
d42/declaration/types/_list_schema.py
d42/declaration/types/_none_schema.py
d42/declaration/types/_optional.py
d42/declaration/types/_schema.py
d42/declaration/types/_str_schema.py
d42/declaration/types/_type_alias_schema.py
d42/declaration/types/_uuid4_schema.py
d42/generation/__init__.py
d42/generation/_consts.py
d42/generation/_generator.py
d42/generation/_random.py
d42/generation/_regex_generator.py
d42/migration/__init__.py
d42/migration/migrate_v1_to_v2.py
d42/representation/__init__.py
d42/representation/_representor.py
d42/substitution/__init__.py
d42/substitution/_substitutor.py
d42/substitution/_validator.py
d42/substitution/errors/__init__.py
d42/utils/__init__.py
d42/utils/_from_native.py
d42/utils/_make_required.py
d42/utils/_rollout.py
d42/validation/__init__.py
d42/validation/_abstract_formatter.py
d42/validation/_formatter.py
d42/validation/_validation_result.py
d42/validation/_validator.py
d42/validation/errors/__init__.py
d42-2.2.0.dist-info/licenses/LICENSE
d42-2.2.0.dist-info/METADATA
d42-2.2.0.dist-info/WHEEL
d42-2.2.0.dist-info/entry_points.txt
d42-2.2.0.dist-info/top_level.txt
d42-2.2.0.dist-info/RECORD
