Metadata-Version: 2.4
Name: d42
Version: 2.2.0
Summary: Toolkit for defining, generating, validating, and substituting data models with a data description language
Home-page: https://github.com/d42-schemas/d42
Author: Nikita Tsvetkov
Author-email: tsv1@fastmail.com
License: Apache-2.0
Project-URL: Docs, https://d42.sh
Project-URL: GitHub, https://github.com/d42-schemas/d42
Classifier: License :: OSI Approved :: Apache Software License
Classifier: Programming Language :: Python :: 3.8
Classifier: Programming Language :: Python :: 3.9
Classifier: Programming Language :: Python :: 3.10
Classifier: Programming Language :: Python :: 3.11
Classifier: Programming Language :: Python :: 3.12
Classifier: Typing :: Typed
Requires-Python: >=3.8
License-File: LICENSE
Requires-Dist: niltype<2.0,>=0.3
Requires-Dist: th<1.0,>=0.3
Dynamic: author
Dynamic: author-email
Dynamic: classifier
Dynamic: description
Dynamic: description-content-type
Dynamic: home-page
Dynamic: license
Dynamic: license-file
Dynamic: project-url
Dynamic: requires-dist
Dynamic: requires-python
Dynamic: summary
